MANIFEST.in
README.rst
setup.py
bin/vennyfiles
bin/vennyplot
pyvenny/__init__.py
pyvenny.egg-info/PKG-INFO
pyvenny.egg-info/SOURCES.txt
pyvenny.egg-info/dependency_links.txt
pyvenny.egg-info/not-zip-safe
pyvenny.egg-info/requires.txt
pyvenny.egg-info/top_level.txt
pyvenny/templates/four_set_venn.svg