Metadata-Version: 1.1
Name: pyvenny
Version: 1.0
Summary: Venn diagram plot of four sets, like venny.
Home-page: http://github.com/CSB-IG/pyvenny
Author: Rodrigo Garcia
Author-email: rgarcia@inmegen.gob.mx
License: GPLv3
Platform: UNKNOWN
Classifier: Development Status :: 4 - Beta
Classifier: License :: OSI Approved :: GNU General Public License v3 (GPLv3)
Classifier: Programming Language :: Python :: 2.7
Classifier: Topic :: Scientific/Engineering :: Visualization
